name_that_fucking_film/__init__.py
name_that_fucking_film/name_that_fucking_film.py
name_that_fucking_film-0.4.0.dist-info/METADATA
name_that_fucking_film-0.4.0.dist-info/WHEEL
name_that_fucking_film-0.4.0.dist-info/entry_points.txt
name_that_fucking_film-0.4.0.dist-info/RECORD
