Metadata-Version: 2.1
Name: name-that-fucking-film
Version: 0.4.0
Summary: 
Author: jkarenko
Author-email: juho.karenko@gmail.com
Requires-Python: >=3.11,<3.12
Classifier: Programming Language :: Python :: 3
Classifier: Programming Language :: Python :: 3.11
Requires-Dist: nltk (>=3.8.1,<4.0.0)
Requires-Dist: pandas (>=2.2.2,<3.0.0)
Requires-Dist: rich (>=13.7.1,<14.0.0)
